{
	"info": {
		"_postman_id": "eb0586b3-dad4-427f-a4bf-cb5d9392246c",
		"name": "OfferCalculatorService",
		"schema": "https://schema.getpostman.com/json/collection/v2.1.0/collection.json",
		"_exporter_id": "42920514"
	},
	"item": [
		{
			"name": "Wycena oferty dla wielu urządzeń",
			"item": [
				{
					"name": "Create device assessment",
					"request": {
						"method": "GET",
						"header": []
					},
					"response": []
				},
				{
					"name": "Offer assessment",
					"request": {
						"method": "GET",
						"header": []
					},
					"response": []
				},
				{
					"name": "Get offer",
					"request": {
						"method": "GET",
						"header": []
					},
					"response": []
				}
			]
		},
		{
			"name": "Wycena oferty urządzenia",
			"item": [
				{
					"name": "Create device assessment",
					"request": {
						"method": "GET",
						"header": []
					},
					"response": []
				},
				{
					"name": "Offer assessment",
					"request": {
						"method": "GET",
						"header": []
					},
					"response": []
				},
				{
					"name": "Get offer",
					"request": {
						"method": "GET",
						"header": []
					},
					"response": []
				}
			]
		},
		{
			"name": "Pobieranie dodanej ceny urządzenia",
			"item": [
				{
					"name": "Get context",
					"request": {
						"method": "GET",
						"header": []
					},
					"response": []
				},
				{
					"name": "Add price",
					"request": {
						"method": "GET",
						"header": []
					},
					"response": []
				},
				{
					"name": "Get pricing tabale record",
					"request": {
						"method": "GET",
						"header": []
					},
					"response": []
				}
			]
		},
		{
			"name": "Import",
			"item": [
				{
					"name": "New Request",
					"request": {
						"method": "GET",
						"header": []
					},
					"response": []
				}
			]
		}
	]
}